LICENSE.md
README.md
orbit_component_base/__init__.py
orbit_component_base/cli/cli_base.py
orbit_component_base/cli/group_permissions.py
orbit_component_base/cli/permissions.py
orbit_component_base/cli/sessions.py
orbit_component_base/cli/users.py
orbit_component_base/plugin.py
orbit_component_base/schema/OrbitGroupPermissions.py
orbit_component_base/schema/OrbitPermissions.py
orbit_component_base/schema/OrbitSessions.py
orbit_component_base/schema/OrbitUsers.py
orbit_component_base/src/orbit_app.py
orbit_component_base/src/orbit_auth.py
orbit_component_base/src/orbit_config.py
orbit_component_base/src/orbit_database.py
orbit_component_base/src/orbit_decorators.py
orbit_component_base/src/orbit_logger.py
orbit_component_base/src/orbit_make_ssl.py
orbit_component_base/src/orbit_nql.py
orbit_component_base/src/orbit_nql_buffer.py
orbit_component_base/src/orbit_nql_emitter.py
orbit_component_base/src/orbit_nql_session.py
orbit_component_base/src/orbit_orm.py
orbit_component_base/src/orbit_plugin.py
orbit_component_base/src/orbit_plugins.py
orbit_component_base/src/orbit_router.py
orbit_component_base/src/orbit_shared.py
orbit_component_base/src/orbit_shells.py
orbit_component_base/tests/test_main.py
orbit_component_base/version.py
orbit_component_base-1.0.51.dist-info/LICENSE.md
orbit_component_base-1.0.51.dist-info/METADATA
orbit_component_base-1.0.51.dist-info/WHEEL
orbit_component_base-1.0.51.dist-info/RECORD
