Metadata-Version: 2.1
Name: orbit-component-base
Version: 1.0.51
Summary: Orbit Framework - base component
Home-page: https://gitlab.com/madpenguin/orbit-component-base
License: MIT
Keywords: orbit-framework,orbit-component,orbit-database
Author: Gareth Bult
Author-email: gareth@madpenguin.uk
Requires-Python: >=3.10,<4.0
Classifier: Development Status :: 4 - Beta
Classifier: Intended Audience :: Developers
Classifier: License :: OSI Approved :: MIT License
Classifier: Operating System :: OS Independent
Classifier: Programming Language :: Python :: 3
Classifier: Programming Language :: Python :: 3.10
Classifier: Programming Language :: Python :: 3.11
Classifier: Programming Language :: Python :: 3.12
Classifier: Topic :: Database :: Database Engines/Servers
Classifier: Topic :: Software Development :: Libraries :: Python Modules
Requires-Dist: aiohttp (>=3,<4)
Requires-Dist: asyncinotify (>=4,<5)
Requires-Dist: loguru (>=0.7,<0.8)
Requires-Dist: orbit-database (>=1.0,<2.0)
Requires-Dist: pycryptodome (>=3.18,<4.0)
Requires-Dist: python-socketio (>=5,<6)
Requires-Dist: rich (>=13,<14)
Requires-Dist: tqdm (>=4,<5)
Requires-Dist: ujson (>=5.7,<6.0)
Project-URL: Documentation, https://gitlab.com/madpenguin/orbit-component-base
Project-URL: Repository, https://gitlab.com/madpenguin/orbit-component-base
